pyexcel_sortable/__init__.py
pyexcel_sortable/sortable.py
pyexcel_sortable-0.0.2.dist-info/DESCRIPTION.rst
pyexcel_sortable-0.0.2.dist-info/METADATA
pyexcel_sortable-0.0.2.dist-info/RECORD
pyexcel_sortable-0.0.2.dist-info/WHEEL
pyexcel_sortable-0.0.2.dist-info/metadata.json
pyexcel_sortable-0.0.2.dist-info/top_level.txt
