Metadata-Version: 2.0
Name: pyexcel-sortable
Version: 0.0.2
Summary: Transform your csv file or a sheet of your xls, xlsx and ods into a sortable HTML file using csvtotable
Home-page: https://github.com/pyexcel/pyexcel-sortable
Author: C.W.
Author-email: wangc_2011@hotmail.com
License: New BSD
Download-URL: https://github.com/pyexcel/pyexcel-sortable/archive/0.0.2.tar.gz
Keywords: python
Platform: UNKNOWN
Classifier: Topic :: Office/Business
Classifier: Topic :: Utilities
Classifier: Topic :: Software Development :: Libraries
Classifier: Programming Language :: Python
Classifier: Intended Audience :: Developers
Classifier: Programming Language :: Python :: 2.6
Classifier: Programming Language :: Python :: 2.7
Classifier: Programming Language :: Python :: 3.3
Classifier: Programming Language :: Python :: 3.4
Classifier: Programming Language :: Python :: 3.5
Classifier: Programming Language :: Python :: 3.6
Requires-Dist: excel2table (>=2.2.0)
